data_transformation_lib_turing_oj/.DS_Store
data_transformation_lib_turing_oj/__init__.py
data_transformation_lib_turing_oj/transformations.py
data_transformation_lib_turing_oj-0.1.0.dist-info/METADATA
data_transformation_lib_turing_oj-0.1.0.dist-info/WHEEL
data_transformation_lib_turing_oj-0.1.0.dist-info/RECORD
