Metadata-Version: 2.1
Name: data_transformation_lib_turing_oj
Version: 0.1.0
Summary: A library for common data transformations
Author: Olga J
Author-email: ppatranka@gmail.com
Requires-Python: >=3.10,<4.0
Classifier: Programming Language :: Python :: 3
Classifier: Programming Language :: Python :: 3.10
Classifier: Programming Language :: Python :: 3.11
Classifier: Programming Language :: Python :: 3.12
Requires-Dist: numpy (>=2.1.1,<3.0.0)
